{
  "config": {
    "step": {
      "user": {
        "title": "Connect to Cerbo GX",
        "description": "Modbus TCP must be enabled on the Cerbo GX under Settings \u2192 Services \u2192 Modbus TCP.",
        "data": {
          "cerbo_host": "Cerbo GX IP Address",
          "modbus_slave": "Modbus Slave / Unit ID",
          "boat_name": "Boat Name"
        },
        "data_description": {
          "cerbo_host": "Local IP of your Cerbo GX, e.g. 192.168.1.100",
          "modbus_slave": "Usually 100 for GPS. Check Cerbo \u2192 Settings \u2192 Services \u2192 Modbus TCP \u2192 Available services",
          "boat_name": "Your boat's name \u2014 used in notifications, e.g. \"NB Persistence\""
        }
      },
      "thresholds": {
        "title": "Mooring Thresholds",
        "description": "How long can the boat stay in one place before you need to move? The Canal & River Trust standard is 14 days.",
        "data": {
          "reminder_days": "Maximum Stay Duration (days)",
          "warning_days": "Reminder Sent On Day"
        },
        "data_description": {
          "reminder_days": "Urgent alerts fire every 12 h once this limit is reached (CRT default: 14)",
          "warning_days": "Gentle heads-up sent on this day, re-sent every 24 h (default: 10)"
        }
      },
      "notifications": {
        "title": "Notification Channels",
        "description": "Choose how you want to be alerted. All settings can be changed later via Configure.",
        "data": {
          "notify_push": "Push Notification",
          "notifier": "Device to Notify",
          "notify_persistent": "Persistent Notifications",
          "notify_email": "Email Notification",
          "smtp_server": "SMTP Server",
          "smtp_port": "SMTP Port",
          "smtp_user": "SMTP Username",
          "smtp_password": "SMTP Password",
          "smtp_recipient": "Recipient Email Address"
        },
        "data_description": {
          "notifier": "e.g. mobile_app_johns_iphone \u2014 find under Settings \u2192 Devices & Services \u2192 Mobile App",
          "smtp_server": "e.g. smtp.gmail.com \u2014 Gmail users: use an App Password from myaccount.google.com/apppasswords",
          "smtp_port": "Usually 587 (STARTTLS)"
        }
      }
    },
    "error": {
      "cannot_connect": "Cannot connect to Cerbo GX \u2014 check the IP address and that Modbus TCP is enabled on port 502.",
      "modbus_error": "Connected but could not read GPS registers \u2014 check the Slave / Unit ID.",
      "notifier_required": "Enter the Companion App notifier name, or disable push notifications.",
      "smtp_required": "SMTP server is required when email notifications are enabled.",
      "recipient_required": "Recipient email address is required when email notifications are enabled."
    },
    "abort": {
      "already_configured": "CC Movement Monitor is already configured for this Cerbo GX."
    }
  },
  "options": {
    "step": {
      "init": {
        "title": "CC Movement Monitor \u2014 Settings",
        "data": {
          "reminder_days": "Maximum Stay Duration (days)",
          "warning_days": "Reminder Sent On Day",
          "notify_push": "Push Notification",
          "notifier": "Device to Notify",
          "notify_persistent": "Persistent Notifications",
          "notify_email": "Email Notification",
          "smtp_server": "SMTP Server",
          "smtp_port": "SMTP Port",
          "smtp_user": "SMTP Username",
          "smtp_password": "SMTP Password",
          "smtp_recipient": "Recipient Email Address"
        }
      }
    },
    "error": {
      "notifier_required": "Enter the Companion App notifier name, or disable push notifications.",
      "recipient_required": "Recipient email address is required when email notifications are enabled."
    }
  }
}